fastapi_oracle/__init__.py
fastapi_oracle/config.py
fastapi_oracle/constants.py
fastapi_oracle/core.py
fastapi_oracle/errors.py
fastapi_oracle/pools.py
fastapi_oracle/utils.py
fastapi_oracle-0.25.0.dist-info/LICENSE
fastapi_oracle-0.25.0.dist-info/METADATA
fastapi_oracle-0.25.0.dist-info/WHEEL
fastapi_oracle-0.25.0.dist-info/RECORD
