Metadata-Version: 2.1
Name: fastapi-oracle
Version: 0.25.0
Summary: Helpers for using the python-oracledb library with the FastAPI framework.
Home-page: https://github.com/Jaza/fastapi-oracle
License: Apache-2.0
Author: Jeremy Epstein
Author-email: jazepstein@gmail.com
Requires-Python: >=3.10,<4
Classifier: License :: OSI Approved :: Apache Software License
Classifier: Programming Language :: Python :: 3
Classifier: Programming Language :: Python :: 3.10
Classifier: Programming Language :: Python :: 3.11
Classifier: Programming Language :: Python :: 3.12
Requires-Dist: fastapi
Requires-Dist: loguru
Requires-Dist: oracledb
Requires-Dist: pydantic-settings
Requires-Dist: pydantic[dotenv] (>=2,<3)
